llama_index/node_parser/dashscope/__init__.py
llama_index/node_parser/dashscope/base.py
llama_index_node_parser_dashscope-0.5.1.dist-info/METADATA
llama_index_node_parser_dashscope-0.5.1.dist-info/WHEEL
llama_index_node_parser_dashscope-0.5.1.dist-info/licenses/LICENSE
llama_index_node_parser_dashscope-0.5.1.dist-info/RECORD
