Metadata-Version: 2.4
Name: llama-index-node-parser-dashscope
Version: 0.5.1
Summary: llama-index node_parser dashscope integration
Author-email: Ruixue Ding <ada.drx@alibaba-inc.com>
License-Expression: MIT
License-File: LICENSE
Requires-Python: <4.0,>=3.9
Requires-Dist: llama-index-core<0.15,>=0.13.0
Requires-Dist: requests
